meta_unicode_lang/__init__.py
meta_unicode_lang/some_module.py
meta_unicode_lang-1.0.1.dist-info/LICENSE.txt
meta_unicode_lang-1.0.1.dist-info/METADATA
meta_unicode_lang-1.0.1.dist-info/WHEEL
meta_unicode_lang-1.0.1.dist-info/top_level.txt
meta_unicode_lang-1.0.1.dist-info/RECORD
