Metadata-Version: 2.1
Name: meta_unicode_lang
Version: 1.0.1
Summary: Meta Unicode Language Framework
Author: Pu Justin Scarfy Yang
Author-email: pujustinscarfyyang@icloud.com
License: MIT
Classifier: License :: OSI Approved :: MIT License
Classifier: Programming Language :: Python :: 3
Classifier: Programming Language :: Python :: 3.10
Classifier: Operating System :: OS Independent
Requires-Python: >=3.7
License-File: LICENSE.txt
Requires-Dist: fusepy
Requires-Dist: pyqt5
Requires-Dist: pygls
